lifehacks/colour/__init__.py
lifehacks/colour/__main__.py
lifehacks/colour/abstract.py
lifehacks/colour/abstract.pyi
lifehacks/colour/hsla.py
lifehacks/colour/hsla.pyi
lifehacks/colour/py.typed
lifehacks/colour/rgba.py
lifehacks/colour/rgba.pyi
lifehacks/colour/palette/__init__.py
lifehacks/colour/palette/__main__.py
lifehacks/colour/palette/apple.py
lifehacks/colour/palette/mariana.py
lifehacks/colour/palette/py.typed
lifehacks.colour-1.2.0.dist-info/LICENSE.md
lifehacks.colour-1.2.0.dist-info/METADATA
lifehacks.colour-1.2.0.dist-info/WHEEL
lifehacks.colour-1.2.0.dist-info/top_level.txt
lifehacks.colour-1.2.0.dist-info/RECORD
