Metadata-Version: 2.1
Name: lifehacks.colour
Version: 1.2.0
Summary: Colour, hsla, rgba, palette
Author: mightbesimon
License: Copyright © 2022 mightbesimon.com
Project-URL: Homepage, https://mightbesimon.com
Project-URL: Source Code, https://github.com/mightbesimon/lifehacks.colour
Project-URL: Documentation, https://github.com/mightbesimon/lifehacks.colour/#readme
Classifier: Intended Audience :: Developers
Classifier: License :: Other/Proprietary License
Classifier: Operating System :: OS Independent
Classifier: Programming Language :: Python :: 3
Classifier: Topic :: Software Development
Classifier: Typing :: Typed
Requires-Python: >=3.7
License-File: LICENSE.md
Requires-Dist: lifehacks.metaclasses
